JaqalPaw_dev-1.1.0b1.data/data/share/jaqalpaw/examples/test_sk1.jaqal
JaqalPaw_dev-1.1.0b1.data/data/share/jaqalpaw/examples/test_sk1.wvf
JaqalPaw_dev-1.1.0b1.data/data/share/jaqalpaw/examples/test_std.jaqal
JaqalPaw_dev-1.1.0b1.data/data/share/jaqalpaw/examples/test_std.wvf
JaqalPaw_dev-1.1.0b1.data/data/share/jaqalpaw/examples/DocumentationSamples/ex14.jaqal
JaqalPaw_dev-1.1.0b1.data/data/share/jaqalpaw/examples/DocumentationSamples/ex14.py
JaqalPaw_dev-1.1.0b1.data/data/share/jaqalpaw/examples/DocumentationSamples/ex14.wvf
JaqalPaw_dev-1.1.0b1.data/data/share/jaqalpaw/examples/DocumentationSamples/ex3.jaqal
JaqalPaw_dev-1.1.0b1.data/data/share/jaqalpaw/examples/DocumentationSamples/ex3.py
JaqalPaw_dev-1.1.0b1.data/data/share/jaqalpaw/examples/DocumentationSamples/ex3.wvf
JaqalPaw_dev-1.1.0b1.data/data/share/jaqalpaw/examples/DocumentationSamples/ex4.jaqal
JaqalPaw_dev-1.1.0b1.data/data/share/jaqalpaw/examples/DocumentationSamples/ex4.py
JaqalPaw_dev-1.1.0b1.data/data/share/jaqalpaw/examples/DocumentationSamples/ex4.wvf
JaqalPaw_dev-1.1.0b1.data/data/share/jaqalpaw/examples/DocumentationSamples/examples_iii_a.jaqal
JaqalPaw_dev-1.1.0b1.data/data/share/jaqalpaw/examples/DocumentationSamples/examples_iii_a.py
JaqalPaw_dev-1.1.0b1.data/data/share/jaqalpaw/examples/DocumentationSamples/examples_iii_a.wvf
JaqalPaw_dev-1.1.0b1.data/data/share/jaqalpaw/examples/DocumentationSamples/examples_iii_b.jaqal
JaqalPaw_dev-1.1.0b1.data/data/share/jaqalpaw/examples/DocumentationSamples/examples_iii_b.py
JaqalPaw_dev-1.1.0b1.data/data/share/jaqalpaw/examples/DocumentationSamples/examples_iii_b.wvf
JaqalPaw_dev-1.1.0b1.data/data/share/jaqalpaw/examples/DocumentationSamples/examples_iv.jaqal
JaqalPaw_dev-1.1.0b1.data/data/share/jaqalpaw/examples/DocumentationSamples/examples_iv.py
JaqalPaw_dev-1.1.0b1.data/data/share/jaqalpaw/examples/DocumentationSamples/examples_iv.wvf
JaqalPaw_dev-1.1.0b1.data/data/share/jaqalpaw/examples/MSGateFrameRotations/Exemplar_MSGateFrameRotations.jaqal
JaqalPaw_dev-1.1.0b1.dist-info/LICENSE
JaqalPaw_dev-1.1.0b1.dist-info/METADATA
JaqalPaw_dev-1.1.0b1.dist-info/NOTICE
JaqalPaw_dev-1.1.0b1.dist-info/WHEEL
JaqalPaw_dev-1.1.0b1.dist-info/entry_points.txt
JaqalPaw_dev-1.1.0b1.dist-info/top_level.txt
JaqalPaw_dev-1.1.0b1.dist-info/RECORD
