Metadata-Version: 2.1
Name: JaqalPaw-dev
Version: 1.1.0b1
Summary: Just Another Quantum Assembly Language Pulses and Waveform Specification
Home-page: https://qscout.sandia.gov
Author: Daniel Lobser, Benjamin C. A. Morrison, Kenneth Rudinger, Antonio Russo, Jay Wesley Van Der Wall
Author-email: qscout@sandia.gov
License: Apache
Classifier: Development Status :: 4 - Beta
Classifier: Intended Audience :: Science/Research
Classifier: License :: OSI Approved :: Apache Software License
Classifier: Programming Language :: Python :: 3
Classifier: Topic :: Scientific/Engineering :: Physics
Classifier: Operating System :: Microsoft :: Windows
Classifier: Operating System :: MacOS :: MacOS X
Classifier: Operating System :: Unix
Requires-Python: >=3.6.5
License-File: LICENSE
License-File: NOTICE
Requires-Dist: numpy
Requires-Dist: scipy
Requires-Dist: JaqalPaq-dev (>=1.1.0b1)
Provides-Extra: emulator
Requires-Dist: matplotlib ; extra == 'emulator'
Provides-Extra: tests
Requires-Dist: pytest ; extra == 'tests'
